reachml/__init__.py
reachml/_version.py
reachml/action_element.py
reachml/action_set.py
reachml/auditor.py
reachml/database.py
reachml/datasets.py
reachml/enumeration.py
reachml/paths.py
reachml/printer.py
reachml/reachable_set.py
reachml/sampling.py
reachml/scoring.py
reachml/utils.py
reachml/constraints/__init__.py
reachml/constraints/abstract.py
reachml/constraints/additive_linkage.py
reachml/constraints/directional_linkage.py
reachml/constraints/ifthen.py
reachml/constraints/linkage.py
reachml/constraints/onehot.py
reachml/constraints/ordinal.py
reachml/constraints/reachability.py
reachml/constraints/switch.py
reachml/constraints/thermometer.py
reachml/mip/__init__.py
reachml/mip/backend_interface.py
reachml/mip/base_mip.py
reachml/mip/enumerator_mip.py
reachml/mip/backends/__init__.py
reachml/mip/backends/cplex.py
reachml/mip/backends/cplex_utils.py
reachml/mip/backends/scip.py
reachml/mip/backends/scip_utils.py
reachml-0.2.1.3.dist-info/METADATA
reachml-0.2.1.3.dist-info/WHEEL
reachml-0.2.1.3.dist-info/licenses/LICENSE
reachml-0.2.1.3.dist-info/RECORD
