Metadata-Version: 2.4
Name: reachml
Version: 0.2.1.3
Summary: Recourse verification with reachable sets
Author-email: Berk Ustun <berk@ucsd.edu>, Bogdan Kulynych <bogdan@kulyny.ch>, Avni Kothrai <akothari@ucsd.edu>, Harry Cheon <scheon@ucsd.edu>, Meredith Stewart <mds010@ucds.edu>
License-Expression: MIT
License-File: LICENSE
Requires-Python: <3.13,>=3.10
Requires-Dist: cplex>=22.1.2
Requires-Dist: docplex>=2.30.251
Requires-Dist: h5py~=3.12.1
Requires-Dist: matplotlib~=3.10.0
Requires-Dist: numpy~=2.1.3
Requires-Dist: pandas~=2.2.3
Requires-Dist: prettytable~=3.14.0
Requires-Dist: pyscipopt>=5.6.0
Requires-Dist: tqdm~=4.67.1
